nebula/__init__.py
nebula/main.py
yt_nebula-1.0.3.dist-info/licenses/LICENSE
yt_nebula-1.0.3.dist-info/METADATA
yt_nebula-1.0.3.dist-info/WHEEL
yt_nebula-1.0.3.dist-info/entry_points.txt
yt_nebula-1.0.3.dist-info/top_level.txt
yt_nebula-1.0.3.dist-info/RECORD
