Metadata-Version: 2.4
Name: YT-Nebula
Version: 1.0.3
Summary: una herramienta mela para youtube
Author: fendrixx
Classifier: Programming Language :: Python :: 3
Classifier: License :: OSI Approved :: MIT License
Classifier: Operating System :: OS Independent
Requires-Python: >=3.8
License-File: LICENSE
Dynamic: license-file
